NorconsultPythonLogger/__init__.py
NorconsultPythonLogger-1.0.0.dist-info/LICENSE.txt
NorconsultPythonLogger-1.0.0.dist-info/METADATA
NorconsultPythonLogger-1.0.0.dist-info/WHEEL
NorconsultPythonLogger-1.0.0.dist-info/top_level.txt
NorconsultPythonLogger-1.0.0.dist-info/RECORD
